geek_mess_server-0.0.1.data/scripts/server_run
server/__init__.py
server/run_server.py
server/common/__init__.py
server/common/decorators.py
server/common/errors.py
server/common/settings.py
server/common/utilites.py
server/log/__init__.py
server/log/client_log_config.py
server/log/server_log_config.py
server/server/__init__.py
server/server/del_user_dialog_ui.py
server/server/descriptors.py
server/server/register_user_ui.py
server/server/server_db.py
server/server/server_gui.py
server/server/server_main.py
server/server/server_ui.py
server/server/set_server_ui.py
server/tests/__init__.py
server/tests/test_server.py
server/tests/test_utilites.py
geek_mess_server-0.0.1.dist-info/METADATA
geek_mess_server-0.0.1.dist-info/WHEEL
geek_mess_server-0.0.1.dist-info/top_level.txt
geek_mess_server-0.0.1.dist-info/RECORD
